COPYING
MANIFEST.in
setup.py
arrowhead/__init__.py
arrowhead/checker.py
arrowhead/core.py
arrowhead/decorators.py
arrowhead/errors.py
arrowhead/inspector.py
arrowhead/main.py
arrowhead.egg-info/PKG-INFO
arrowhead.egg-info/SOURCES.txt
arrowhead.egg-info/dependency_links.txt
arrowhead.egg-info/top_level.txt
examples/infinite.py
examples/tutorial1.py
examples/tutorial2.py
examples/tutorial3.py
examples/tutorial4.py
examples/tutorial5.py