Metadata-Version: 1.1
Name: arrowhead
Version: 1.0a1
Summary: micro-framework for flowchart-like computing
Home-page: https://github.com/zyga/arrowhead
Author: Zygmunt Krynicki
Author-email: <zkrynicki@gmail.com>
License: BSD
Platform: UNKNOWN
Classifier: Development Status :: 1 - Planning
Classifier: Environment :: Console
Classifier: Intended Audience :: Developers
Classifier: License :: OSI Approved :: GNU Lesser General Public License v3 or later (LGPLv3+)
Classifier: Operating System :: OS Independent
Classifier: Programming Language :: Python
Classifier: Programming Language :: Python :: 3
Classifier: Programming Language :: Python :: 3.2
Classifier: Programming Language :: Python :: 3.3
Classifier: Programming Language :: Python :: Implementation :: CPython
Classifier: Topic :: Software Development :: Libraries :: Application Frameworks
